eodhd/__init__.py
eodhd/apiclient.py
eodhd/eodhdgraphs.py
eodhd/websocketclient.py
eodhd/APIs/BaseAPI.py
eodhd/APIs/BondsFundamentalsAPI.py
eodhd/APIs/BulkEodSplitsDividendsAPI.py
eodhd/APIs/EarningTrendsAPI.py
eodhd/APIs/EconomicEventsDataAPI.py
eodhd/APIs/EodHistoricalStockMarketDataAPI.py
eodhd/APIs/FinancialNewsAPI.py
eodhd/APIs/FundamentalDataAPI.py
eodhd/APIs/HistoricalDividendsAPI.py
eodhd/APIs/HistoricalMarketCapitalizationAPI.py
eodhd/APIs/HistoricalSplitsAPI.py
eodhd/APIs/InsiderTransactionsAPI.py
eodhd/APIs/IntradayDataAPI.py
eodhd/APIs/ListOfExchangesAPI.py
eodhd/APIs/LiveStockPricesAPI.py
eodhd/APIs/MacroIndicatorsAPI.py
eodhd/APIs/OptionsDataAPI.py
eodhd/APIs/StockMarketScreenerAPI.py
eodhd/APIs/StockMarketTickDataAPI.py
eodhd/APIs/TechnicalIndicatorAPI.py
eodhd/APIs/TradingHours_StockMarketHolidays_SymbolsChangeHistory.py
eodhd/APIs/UpcomingEarningsAPI.py
eodhd/APIs/UpcomingIPOsAPI.py
eodhd/APIs/UpcomingSplitsAPI.py
eodhd/APIs/__init__.py
eodhd-1.0.31.dist-info/LICENSE
eodhd-1.0.31.dist-info/METADATA
eodhd-1.0.31.dist-info/WHEEL
eodhd-1.0.31.dist-info/entry_points.txt
eodhd-1.0.31.dist-info/top_level.txt
eodhd-1.0.31.dist-info/RECORD
