Metadata-Version: 2.1
Name: eodhd
Version: 1.0.31
Summary: Official EODHD API Python Library
Home-page: https://whittle.medium.com
Author: Michael Whittle
Author-email: michael@lifecycle-ps.com
License: MIT
Classifier: Intended Audience :: Developers
Classifier: License :: OSI Approved :: MIT License
Classifier: Programming Language :: Python :: 3
Classifier: Programming Language :: Python :: 3.11
Classifier: Operating System :: OS Independent
License-File: LICENSE
Requires-Dist: websockets >=11.0.3
Requires-Dist: websocket-client >=1.6.3
Requires-Dist: requests >=2.31.0
Requires-Dist: rich >=13.5.2
Requires-Dist: pandas >=2.1.0
Requires-Dist: numpy >=1.25.2
Requires-Dist: matplotlib >=3.7.2
